Workbook

Sheet Summary
A1: Revenue forecast summary
A2: Commission earned per month at three points, plus totals. Target from the business plan: £10,000/month by month 24.
A4: Scenario | B4: Month 6 (Mar 2027) £/mo | C4: Month 12 (Sep 2027) £/mo | D4: Month 24 (Sep 2028) £/mo | E4: Year 1 total £ | F4: Year 2 total £ | G4: 24-month net after Tailwind £ | H4: Month 24 as % of £10k target
A5: Low | B5: =Forecast!G11 -> 0.210375 | C5: =Forecast!G17 -> 0.462825 | D5: =Forecast!G29 -> 0.967725 | E5: =Forecast!G31 -> 2.8281114 | F5: =Forecast!G32 -> 8.93673 | G5: =Forecast!H33 -> -540.23516 | H5: =Forecast!G29/$B$9 -> 9.67725e-05
A6: Base | B6: =Forecast!O11 -> 4.85625 | C6: =Forecast!O17 -> 10.68375 | D6: =Forecast!O29 -> 22.33875 | E6: =Forecast!O31 -> 65.28963 | F6: =Forecast!O32 -> 206.2935 | G6: =Forecast!P33 -> -280.41687 | H6: =Forecast!O29/$B$9 -> 0.002233875
A7: High | B7: =Forecast!W11 -> 75.796875 | C7: =Forecast!W17 -> 166.75313 | D7: =Forecast!W29 -> 348.66562 | E7: =Forecast!W31 -> 1019.2723 | F7: =Forecast!W32 -> 3219.8513 | G7: =Forecast!X33 -> 3687.1235 | H7: =Forecast!W29/$B$9 -> 0.034866563
A9: Target (£/month) | B9: 10000

Sheet Assumptions
A1: Revenue forecast – assumptions
A2: Blue = editable inputs. Estimates, not verified benchmarks, unless the note cites a source. Months 7–24 extend the first six months' trend; nothing new is assumed beyond that.
A4: Driver | B4: Low | C4: Base | D4: High | E4: Note / source
A5: Impressions multiplier vs base path | B5: 0.4 | C5: 1 | D5: 2.5 | E5: Scales the monthly impressions path below. Estimate.
A6: Outbound click rate (impressions → site visits) | B6: 0.003 | C6: 0.006 | D6: 0.01 | E6: Estimate – no verified Pinterest benchmark used.
A7: Site visit → affiliate link click | B7: 0.15 | C7: 0.25 | D7: 0.35 | E7: Estimate.
A8: Amazon conversion (click → order) | B8: 0.03 | C8: 0.05 | D8: 0.08 | E8: Estimate.
A9: Amazon average basket (£) | B9: 25 | C9: 35 | D9: 45 | E9: Estimate.
A10: Amazon commission rate | B10: 0.025 | C10: 0.03 | D10: 0.04 | E10: Estimate – check Amazon UK Associates fee schedule.
A11: Awin conversion (click → order) | B11: 0.014 | C11: 0.02 | D11: 0.03 | E11: Awin directory, 12 Oct 2026: Meaco 1.44%, Ebac 1.51%, AO 2.02%, Currys 2.99%.
A12: Awin average order (£) | B12: 80 | C12: 110 | D12: 150 | E12: Estimate – airers £55–£160, dehumidifiers £140–£350 (Which?, Oct 2026).
A13: Awin commission rate (blended) | B13: 0.025 | C13: 0.035 | D13: 0.045 | E13: Retailer terms: Ebac 5%, Meaco 4%, Beldray 5%, Lakeland 2.5%, The Range 2%.
A14: Tailwind cost (£/month) | B14: 23 | C14: 23 | D14: 23 | E14: $29.99/month plan; £ approximate.
A16: Base impressions added per month after Mar 2027 | C16: 10000 | E16: Linear continuation of the Feb→Mar 2027 step (+12,000). Applies to all scenarios via the multiplier.
A18: Month | B18: Base impressions | C18: Share of clicks to Awin | D18: Seasonality (conversion) | E18: Note
A19: Oct 2026 | B19: 2000 | C19: 0 | D19: 1 | E19: Part month; photo pins live from 12 Oct
A20: Nov 2026 | B20: 12000 | C20: 0.3 | D20: 1.1
A21: Dec 2026 | B21: 30000 | C21: 0.5 | D21: 1.3 | E21: Christmas peak
A22: Jan 2027 | B22: 28000 | C22: 0.5 | D22: 0.9
A23: Feb 2027 | B23: 38000 | C23: 0.5 | D23: 0.9
A24: Mar 2027 | B24: 50000 | C24: 0.5 | D24: 1
A25: Apr 2027 | B25: =B24+$C$16 -> 60000 | C25: 0.5 | D25: 1
A26: May 2027 | B26: =B25+$C$16 -> 70000 | C26: 0.5 | D26: 1
A27: Jun 2027 | B27: =B26+$C$16 -> 80000 | C27: 0.5 | D27: 1
A28: Jul 2027 | B28: =B27+$C$16 -> 90000 | C28: 0.5 | D28: 1
A29: Aug 2027 | B29: =B28+$C$16 -> 100000 | C29: 0.5 | D29: 1
A30: Sep 2027 | B30: =B29+$C$16 -> 110000 | C30: 0.5 | D30: 1
A31: Oct 2027 | B31: =B30+$C$16 -> 120000 | C31: 0.5 | D31: 1 | E31: Christmas peak
A32: Nov 2027 | B32: =B31+$C$16 -> 130000 | C32: 0.5 | D32: 1.1
A33: Dec 2027 | B33: =B32+$C$16 -> 140000 | C33: 0.5 | D33: 1.3
A34: Jan 2028 | B34: =B33+$C$16 -> 150000 | C34: 0.5 | D34: 0.9
A35: Feb 2028 | B35: =B34+$C$16 -> 160000 | C35: 0.5 | D35: 0.9
A36: Mar 2028 | B36: =B35+$C$16 -> 170000 | C36: 0.5 | D36: 1
A37: Apr 2028 | B37: =B36+$C$16 -> 180000 | C37: 0.5 | D37: 1
A38: May 2028 | B38: =B37+$C$16 -> 190000 | C38: 0.5 | D38: 1
A39: Jun 2028 | B39: =B38+$C$16 -> 200000 | C39: 0.5 | D39: 1
A40: Jul 2028 | B40: =B39+$C$16 -> 210000 | C40: 0.5 | D40: 1
A41: Aug 2028 | B41: =B40+$C$16 -> 220000 | C41: 0.5 | D41: 1
A42: Sep 2028 | B42: =B41+$C$16 -> 230000 | C42: 0.5 | D42: 1

Sheet Forecast
A1: 24-month revenue forecast – commission earned (before payout delays)
A2: Amazon and Awin pay weeks to months after the sale, so cash arrives later than shown.
B4: Low case | J4: Base case | R4: High case
A5: Month | B5: Impressions | C5: Site visits | D5: Affiliate clicks | E5: Amazon orders | F5: Awin orders | G5: Commission (£) | H5: Net after Tailwind (£) | I5: Cum. Amazon orders | J5: Impressions | K5: Site visits | L5: Affiliate clicks | M5: Amazon orders | N5: Awin orders | O5: Commission (£) | P5: Net after Tailwind (£) | Q5: Cum. Amazon orders | R5: Impressions | S5: Site visits | T5: Affiliate clicks | U5: Amazon orders | V5: Awin orders | W5: Commission (£) | X5: Net after Tailwind (£) | Y5: Cum. Amazon orders
A6: =Assumptions!A19 -> Oct 2026 | B6: =Assumptions!B19*Assumptions!$B$5 -> 800 | C6: =B6*Assumptions!$B$6 -> 2.4 | D6: =C6*Assumptions!$B$7 -> 0.36 | E6: =D6*(1-Assumptions!C19)*Assumptions!$B$8*Assumptions!D19 -> 0.0108 | F6: =D6*Assumptions!C19*Assumptions!$B$11*Assumptions!D19 -> 0 | G6: =E6*Assumptions!$B$9*Assumptions!$B$10+F6*Assumptions!$B$12*Assumptions!$B$13 -> 0.00675 | H6: =G6-Assumptions!$B$14 -> -22.99325 | I6: =SUM(E$6:E6) -> 0.0108 | J6: =Assumptions!B19*Assumptions!$C$5 -> 2000 | K6: =J6*Assumptions!$C$6 -> 12 | L6: =K6*Assumptions!$C$7 -> 3 | M6: =L6*(1-Assumptions!C19)*Assumptions!$C$8*Assumptions!D19 -> 0.15 | N6: =L6*Assumptions!C19*Assumptions!$C$11*Assumptions!D19 -> 0 | O6: =M6*Assumptions!$C$9*Assumptions!$C$10+N6*Assumptions!$C$12*Assumptions!$C$13 -> 0.1575 | P6: =O6-Assumptions!$C$14 -> -22.8425 | Q6: =SUM(M$6:M6) -> 0.15 | R6: =Assumptions!B19*Assumptions!$D$5 -> 5000 | S6: =R6*Assumptions!$D$6 -> 50 | T6: =S6*Assumptions!$D$7 -> 17.5 | U6: =T6*(1-Assumptions!C19)*Assumptions!$D$8*Assumptions!D19 -> 1.4 | V6: =T6*Assumptions!C19*Assumptions!$D$11*Assumptions!D19 -> 0 | W6: =U6*Assumptions!$D$9*Assumptions!$D$10+V6*Assumptions!$D$12*Assumptions!$D$13 -> 2.52 | X6: =W6-Assumptions!$D$14 -> -20.48 | Y6: =SUM(U$6:U6) -> 1.4
A7: =Assumptions!A20 -> Nov 2026 | B7: =Assumptions!B20*Assumptions!$B$5 -> 4800 | C7: =B7*Assumptions!$B$6 -> 14.4 | D7: =C7*Assumptions!$B$7 -> 2.16 | E7: =D7*(1-Assumptions!C20)*Assumptions!$B$8*Assumptions!D20 -> 0.049896 | F7: =D7*Assumptions!C20*Assumptions!$B$11*Assumptions!D20 -> 0.0099792 | G7: =E7*Assumptions!$B$9*Assumptions!$B$10+F7*Assumptions!$B$12*Assumptions!$B$13 -> 0.0511434 | H7: =G7-Assumptions!$B$14 -> -22.948857 | I7: =SUM(E$6:E7) -> 0.060696 | J7: =Assumptions!B20*Assumptions!$C$5 -> 12000 | K7: =J7*Assumptions!$C$6 -> 72 | L7: =K7*Assumptions!$C$7 -> 18 | M7: =L7*(1-Assumptions!C20)*Assumptions!$C$8*Assumptions!D20 -> 0.693 | N7: =L7*Assumptions!C20*Assumptions!$C$11*Assumptions!D20 -> 0.1188 | O7: =M7*Assumptions!$C$9*Assumptions!$C$10+N7*Assumptions!$C$12*Assumptions!$C$13 -> 1.18503 | P7: =O7-Assumptions!$C$14 -> -21.81497 | Q7: =SUM(M$6:M7) -> 0.843 | R7: =Assumptions!B20*Assumptions!$D$5 -> 30000 | S7: =R7*Assumptions!$D$6 -> 300 | T7: =S7*Assumptions!$D$7 -> 105 | U7: =T7*(1-Assumptions!C20)*Assumptions!$D$8*Assumptions!D20 -> 6.468 | V7: =T7*Assumptions!C20*Assumptions!$D$11*Assumptions!D20 -> 1.0395 | W7: =U7*Assumptions!$D$9*Assumptions!$D$10+V7*Assumptions!$D$12*Assumptions!$D$13 -> 18.659025 | X7: =W7-Assumptions!$D$14 -> -4.340975 | Y7: =SUM(U$6:U7) -> 7.868
A8: =Assumptions!A21 -> Dec 2026 | B8: =Assumptions!B21*Assumptions!$B$5 -> 12000 | C8: =B8*Assumptions!$B$6 -> 36 | D8: =C8*Assumptions!$B$7 -> 5.4 | E8: =D8*(1-Assumptions!C21)*Assumptions!$B$8*Assumptions!D21 -> 0.1053 | F8: =D8*Assumptions!C21*Assumptions!$B$11*Assumptions!D21 -> 0.04914 | G8: =E8*Assumptions!$B$9*Assumptions!$B$10+F8*Assumptions!$B$12*Assumptions!$B$13 -> 0.1640925 | H8: =G8-Assumptions!$B$14 -> -22.835908 | I8: =SUM(E$6:E8) -> 0.165996 | J8: =Assumptions!B21*Assumptions!$C$5 -> 30000 | K8: =J8*Assumptions!$C$6 -> 180 | L8: =K8*Assumptions!$C$7 -> 45 | M8: =L8*(1-Assumptions!C21)*Assumptions!$C$8*Assumptions!D21 -> 1.4625 | N8: =L8*Assumptions!C21*Assumptions!$C$11*Assumptions!D21 -> 0.585 | O8: =M8*Assumptions!$C$9*Assumptions!$C$10+N8*Assumptions!$C$12*Assumptions!$C$13 -> 3.787875 | P8: =O8-Assumptions!$C$14 -> -19.212125 | Q8: =SUM(M$6:M8) -> 2.3055 | R8: =Assumptions!B21*Assumptions!$D$5 -> 75000 | S8: =R8*Assumptions!$D$6 -> 750 | T8: =S8*Assumptions!$D$7 -> 262.5 | U8: =T8*(1-Assumptions!C21)*Assumptions!$D$8*Assumptions!D21 -> 13.65 | V8: =T8*Assumptions!C21*Assumptions!$D$11*Assumptions!D21 -> 5.11875 | W8: =U8*Assumptions!$D$9*Assumptions!$D$10+V8*Assumptions!$D$12*Assumptions!$D$13 -> 59.121563 | X8: =W8-Assumptions!$D$14 -> 36.121563 | Y8: =SUM(U$6:U8) -> 21.518
A9: =Assumptions!A22 -> Jan 2027 | B9: =Assumptions!B22*Assumptions!$B$5 -> 11200 | C9: =B9*Assumptions!$B$6 -> 33.6 | D9: =C9*Assumptions!$B$7 -> 5.04 | E9: =D9*(1-Assumptions!C22)*Assumptions!$B$8*Assumptions!D22 -> 0.06804 | F9: =D9*Assumptions!C22*Assumptions!$B$11*Assumptions!D22 -> 0.031752 | G9: =E9*Assumptions!$B$9*Assumptions!$B$10+F9*Assumptions!$B$12*Assumptions!$B$13 -> 0.106029 | H9: =G9-Assumptions!$B$14 -> -22.893971 | I9: =SUM(E$6:E9) -> 0.234036 | J9: =Assumptions!B22*Assumptions!$C$5 -> 28000 | K9: =J9*Assumptions!$C$6 -> 168 | L9: =K9*Assumptions!$C$7 -> 42 | M9: =L9*(1-Assumptions!C22)*Assumptions!$C$8*Assumptions!D22 -> 0.945 | N9: =L9*Assumptions!C22*Assumptions!$C$11*Assumptions!D22 -> 0.378 | O9: =M9*Assumptions!$C$9*Assumptions!$C$10+N9*Assumptions!$C$12*Assumptions!$C$13 -> 2.44755 | P9: =O9-Assumptions!$C$14 -> -20.55245 | Q9: =SUM(M$6:M9) -> 3.2505 | R9: =Assumptions!B22*Assumptions!$D$5 -> 70000 | S9: =R9*Assumptions!$D$6 -> 700 | T9: =S9*Assumptions!$D$7 -> 245 | U9: =T9*(1-Assumptions!C22)*Assumptions!$D$8*Assumptions!D22 -> 8.82 | V9: =T9*Assumptions!C22*Assumptions!$D$11*Assumptions!D22 -> 3.3075 | W9: =U9*Assumptions!$D$9*Assumptions!$D$10+V9*Assumptions!$D$12*Assumptions!$D$13 -> 38.201625 | X9: =W9-Assumptions!$D$14 -> 15.201625 | Y9: =SUM(U$6:U9) -> 30.338
A10: =Assumptions!A23 -> Feb 2027 | B10: =Assumptions!B23*Assumptions!$B$5 -> 15200 | C10: =B10*Assumptions!$B$6 -> 45.6 | D10: =C10*Assumptions!$B$7 -> 6.84 | E10: =D10*(1-Assumptions!C23)*Assumptions!$B$8*Assumptions!D23 -> 0.09234 | F10: =D10*Assumptions!C23*Assumptions!$B$11*Assumptions!D23 -> 0.043092 | G10: =E10*Assumptions!$B$9*Assumptions!$B$10+F10*Assumptions!$B$12*Assumptions!$B$13 -> 0.1438965 | H10: =G10-Assumptions!$B$14 -> -22.856103 | I10: =SUM(E$6:E10) -> 0.326376 | J10: =Assumptions!B23*Assumptions!$C$5 -> 38000 | K10: =J10*Assumptions!$C$6 -> 228 | L10: =K10*Assumptions!$C$7 -> 57 | M10: =L10*(1-Assumptions!C23)*Assumptions!$C$8*Assumptions!D23 -> 1.2825 | N10: =L10*Assumptions!C23*Assumptions!$C$11*Assumptions!D23 -> 0.513 | O10: =M10*Assumptions!$C$9*Assumptions!$C$10+N10*Assumptions!$C$12*Assumptions!$C$13 -> 3.321675 | P10: =O10-Assumptions!$C$14 -> -19.678325 | Q10: =SUM(M$6:M10) -> 4.533 | R10: =Assumptions!B23*Assumptions!$D$5 -> 95000 | S10: =R10*Assumptions!$D$6 -> 950 | T10: =S10*Assumptions!$D$7 -> 332.5 | U10: =T10*(1-Assumptions!C23)*Assumptions!$D$8*Assumptions!D23 -> 11.97 | V10: =T10*Assumptions!C23*Assumptions!$D$11*Assumptions!D23 -> 4.48875 | W10: =U10*Assumptions!$D$9*Assumptions!$D$10+V10*Assumptions!$D$12*Assumptions!$D$13 -> 51.845062 | X10: =W10-Assumptions!$D$14 -> 28.845063 | Y10: =SUM(U$6:U10) -> 42.308
A11: =Assumptions!A24 -> Mar 2027 | B11: =Assumptions!B24*Assumptions!$B$5 -> 20000 | C11: =B11*Assumptions!$B$6 -> 60 | D11: =C11*Assumptions!$B$7 -> 9 | E11: =D11*(1-Assumptions!C24)*Assumptions!$B$8*Assumptions!D24 -> 0.135 | F11: =D11*Assumptions!C24*Assumptions!$B$11*Assumptions!D24 -> 0.063 | G11: =E11*Assumptions!$B$9*Assumptions!$B$10+F11*Assumptions!$B$12*Assumptions!$B$13 -> 0.210375 | H11: =G11-Assumptions!$B$14 -> -22.789625 | I11: =SUM(E$6:E11) -> 0.461376 | J11: =Assumptions!B24*Assumptions!$C$5 -> 50000 | K11: =J11*Assumptions!$C$6 -> 300 | L11: =K11*Assumptions!$C$7 -> 75 | M11: =L11*(1-Assumptions!C24)*Assumptions!$C$8*Assumptions!D24 -> 1.875 | N11: =L11*Assumptions!C24*Assumptions!$C$11*Assumptions!D24 -> 0.75 | O11: =M11*Assumptions!$C$9*Assumptions!$C$10+N11*Assumptions!$C$12*Assumptions!$C$13 -> 4.85625 | P11: =O11-Assumptions!$C$14 -> -18.14375 | Q11: =SUM(M$6:M11) -> 6.408 | R11: =Assumptions!B24*Assumptions!$D$5 -> 125000 | S11: =R11*Assumptions!$D$6 -> 1250 | T11: =S11*Assumptions!$D$7 -> 437.5 | U11: =T11*(1-Assumptions!C24)*Assumptions!$D$8*Assumptions!D24 -> 17.5 | V11: =T11*Assumptions!C24*Assumptions!$D$11*Assumptions!D24 -> 6.5625 | W11: =U11*Assumptions!$D$9*Assumptions!$D$10+V11*Assumptions!$D$12*Assumptions!$D$13 -> 75.796875 | X11: =W11-Assumptions!$D$14 -> 52.796875 | Y11: =SUM(U$6:U11) -> 59.808
A12: =Assumptions!A25 -> Apr 2027 | B12: =Assumptions!B25*Assumptions!$B$5 -> 24000 | C12: =B12*Assumptions!$B$6 -> 72 | D12: =C12*Assumptions!$B$7 -> 10.8 | E12: =D12*(1-Assumptions!C25)*Assumptions!$B$8*Assumptions!D25 -> 0.162 | F12: =D12*Assumptions!C25*Assumptions!$B$11*Assumptions!D25 -> 0.0756 | G12: =E12*Assumptions!$B$9*Assumptions!$B$10+F12*Assumptions!$B$12*Assumptions!$B$13 -> 0.25245 | H12: =G12-Assumptions!$B$14 -> -22.74755 | I12: =SUM(E$6:E12) -> 0.623376 | J12: =Assumptions!B25*Assumptions!$C$5 -> 60000 | K12: =J12*Assumptions!$C$6 -> 360 | L12: =K12*Assumptions!$C$7 -> 90 | M12: =L12*(1-Assumptions!C25)*Assumptions!$C$8*Assumptions!D25 -> 2.25 | N12: =L12*Assumptions!C25*Assumptions!$C$11*Assumptions!D25 -> 0.9 | O12: =M12*Assumptions!$C$9*Assumptions!$C$10+N12*Assumptions!$C$12*Assumptions!$C$13 -> 5.8275 | P12: =O12-Assumptions!$C$14 -> -17.1725 | Q12: =SUM(M$6:M12) -> 8.658 | R12: =Assumptions!B25*Assumptions!$D$5 -> 150000 | S12: =R12*Assumptions!$D$6 -> 1500 | T12: =S12*Assumptions!$D$7 -> 525 | U12: =T12*(1-Assumptions!C25)*Assumptions!$D$8*Assumptions!D25 -> 21 | V12: =T12*Assumptions!C25*Assumptions!$D$11*Assumptions!D25 -> 7.875 | W12: =U12*Assumptions!$D$9*Assumptions!$D$10+V12*Assumptions!$D$12*Assumptions!$D$13 -> 90.95625 | X12: =W12-Assumptions!$D$14 -> 67.95625 | Y12: =SUM(U$6:U12) -> 80.808
A13: =Assumptions!A26 -> May 2027 | B13: =Assumptions!B26*Assumptions!$B$5 -> 28000 | C13: =B13*Assumptions!$B$6 -> 84 | D13: =C13*Assumptions!$B$7 -> 12.6 | E13: =D13*(1-Assumptions!C26)*Assumptions!$B$8*Assumptions!D26 -> 0.189 | F13: =D13*Assumptions!C26*Assumptions!$B$11*Assumptions!D26 -> 0.0882 | G13: =E13*Assumptions!$B$9*Assumptions!$B$10+F13*Assumptions!$B$12*Assumptions!$B$13 -> 0.294525 | H13: =G13-Assumptions!$B$14 -> -22.705475 | I13: =SUM(E$6:E13) -> 0.812376 | J13: =Assumptions!B26*Assumptions!$C$5 -> 70000 | K13: =J13*Assumptions!$C$6 -> 420 | L13: =K13*Assumptions!$C$7 -> 105 | M13: =L13*(1-Assumptions!C26)*Assumptions!$C$8*Assumptions!D26 -> 2.625 | N13: =L13*Assumptions!C26*Assumptions!$C$11*Assumptions!D26 -> 1.05 | O13: =M13*Assumptions!$C$9*Assumptions!$C$10+N13*Assumptions!$C$12*Assumptions!$C$13 -> 6.79875 | P13: =O13-Assumptions!$C$14 -> -16.20125 | Q13: =SUM(M$6:M13) -> 11.283 | R13: =Assumptions!B26*Assumptions!$D$5 -> 175000 | S13: =R13*Assumptions!$D$6 -> 1750 | T13: =S13*Assumptions!$D$7 -> 612.5 | U13: =T13*(1-Assumptions!C26)*Assumptions!$D$8*Assumptions!D26 -> 24.5 | V13: =T13*Assumptions!C26*Assumptions!$D$11*Assumptions!D26 -> 9.1875 | W13: =U13*Assumptions!$D$9*Assumptions!$D$10+V13*Assumptions!$D$12*Assumptions!$D$13 -> 106.11562 | X13: =W13-Assumptions!$D$14 -> 83.115625 | Y13: =SUM(U$6:U13) -> 105.308
A14: =Assumptions!A27 -> Jun 2027 | B14: =Assumptions!B27*Assumptions!$B$5 -> 32000 | C14: =B14*Assumptions!$B$6 -> 96 | D14: =C14*Assumptions!$B$7 -> 14.4 | E14: =D14*(1-Assumptions!C27)*Assumptions!$B$8*Assumptions!D27 -> 0.216 | F14: =D14*Assumptions!C27*Assumptions!$B$11*Assumptions!D27 -> 0.1008 | G14: =E14*Assumptions!$B$9*Assumptions!$B$10+F14*Assumptions!$B$12*Assumptions!$B$13 -> 0.3366 | H14: =G14-Assumptions!$B$14 -> -22.6634 | I14: =SUM(E$6:E14) -> 1.028376 | J14: =Assumptions!B27*Assumptions!$C$5 -> 80000 | K14: =J14*Assumptions!$C$6 -> 480 | L14: =K14*Assumptions!$C$7 -> 120 | M14: =L14*(1-Assumptions!C27)*Assumptions!$C$8*Assumptions!D27 -> 3 | N14: =L14*Assumptions!C27*Assumptions!$C$11*Assumptions!D27 -> 1.2 | O14: =M14*Assumptions!$C$9*Assumptions!$C$10+N14*Assumptions!$C$12*Assumptions!$C$13 -> 7.77 | P14: =O14-Assumptions!$C$14 -> -15.23 | Q14: =SUM(M$6:M14) -> 14.283 | R14: =Assumptions!B27*Assumptions!$D$5 -> 200000 | S14: =R14*Assumptions!$D$6 -> 2000 | T14: =S14*Assumptions!$D$7 -> 700 | U14: =T14*(1-Assumptions!C27)*Assumptions!$D$8*Assumptions!D27 -> 28 | V14: =T14*Assumptions!C27*Assumptions!$D$11*Assumptions!D27 -> 10.5 | W14: =U14*Assumptions!$D$9*Assumptions!$D$10+V14*Assumptions!$D$12*Assumptions!$D$13 -> 121.275 | X14: =W14-Assumptions!$D$14 -> 98.275 | Y14: =SUM(U$6:U14) -> 133.308
A15: =Assumptions!A28 -> Jul 2027 | B15: =Assumptions!B28*Assumptions!$B$5 -> 36000 | C15: =B15*Assumptions!$B$6 -> 108 | D15: =C15*Assumptions!$B$7 -> 16.2 | E15: =D15*(1-Assumptions!C28)*Assumptions!$B$8*Assumptions!D28 -> 0.243 | F15: =D15*Assumptions!C28*Assumptions!$B$11*Assumptions!D28 -> 0.1134 | G15: =E15*Assumptions!$B$9*Assumptions!$B$10+F15*Assumptions!$B$12*Assumptions!$B$13 -> 0.378675 | H15: =G15-Assumptions!$B$14 -> -22.621325 | I15: =SUM(E$6:E15) -> 1.271376 | J15: =Assumptions!B28*Assumptions!$C$5 -> 90000 | K15: =J15*Assumptions!$C$6 -> 540 | L15: =K15*Assumptions!$C$7 -> 135 | M15: =L15*(1-Assumptions!C28)*Assumptions!$C$8*Assumptions!D28 -> 3.375 | N15: =L15*Assumptions!C28*Assumptions!$C$11*Assumptions!D28 -> 1.35 | O15: =M15*Assumptions!$C$9*Assumptions!$C$10+N15*Assumptions!$C$12*Assumptions!$C$13 -> 8.74125 | P15: =O15-Assumptions!$C$14 -> -14.25875 | Q15: =SUM(M$6:M15) -> 17.658 | R15: =Assumptions!B28*Assumptions!$D$5 -> 225000 | S15: =R15*Assumptions!$D$6 -> 2250 | T15: =S15*Assumptions!$D$7 -> 787.5 | U15: =T15*(1-Assumptions!C28)*Assumptions!$D$8*Assumptions!D28 -> 31.5 | V15: =T15*Assumptions!C28*Assumptions!$D$11*Assumptions!D28 -> 11.8125 | W15: =U15*Assumptions!$D$9*Assumptions!$D$10+V15*Assumptions!$D$12*Assumptions!$D$13 -> 136.43437 | X15: =W15-Assumptions!$D$14 -> 113.43438 | Y15: =SUM(U$6:U15) -> 164.808
A16: =Assumptions!A29 -> Aug 2027 | B16: =Assumptions!B29*Assumptions!$B$5 -> 40000 | C16: =B16*Assumptions!$B$6 -> 120 | D16: =C16*Assumptions!$B$7 -> 18 | E16: =D16*(1-Assumptions!C29)*Assumptions!$B$8*Assumptions!D29 -> 0.27 | F16: =D16*Assumptions!C29*Assumptions!$B$11*Assumptions!D29 -> 0.126 | G16: =E16*Assumptions!$B$9*Assumptions!$B$10+F16*Assumptions!$B$12*Assumptions!$B$13 -> 0.42075 | H16: =G16-Assumptions!$B$14 -> -22.57925 | I16: =SUM(E$6:E16) -> 1.541376 | J16: =Assumptions!B29*Assumptions!$C$5 -> 100000 | K16: =J16*Assumptions!$C$6 -> 600 | L16: =K16*Assumptions!$C$7 -> 150 | M16: =L16*(1-Assumptions!C29)*Assumptions!$C$8*Assumptions!D29 -> 3.75 | N16: =L16*Assumptions!C29*Assumptions!$C$11*Assumptions!D29 -> 1.5 | O16: =M16*Assumptions!$C$9*Assumptions!$C$10+N16*Assumptions!$C$12*Assumptions!$C$13 -> 9.7125 | P16: =O16-Assumptions!$C$14 -> -13.2875 | Q16: =SUM(M$6:M16) -> 21.408 | R16: =Assumptions!B29*Assumptions!$D$5 -> 250000 | S16: =R16*Assumptions!$D$6 -> 2500 | T16: =S16*Assumptions!$D$7 -> 875 | U16: =T16*(1-Assumptions!C29)*Assumptions!$D$8*Assumptions!D29 -> 35 | V16: =T16*Assumptions!C29*Assumptions!$D$11*Assumptions!D29 -> 13.125 | W16: =U16*Assumptions!$D$9*Assumptions!$D$10+V16*Assumptions!$D$12*Assumptions!$D$13 -> 151.59375 | X16: =W16-Assumptions!$D$14 -> 128.59375 | Y16: =SUM(U$6:U16) -> 199.808
A17: =Assumptions!A30 -> Sep 2027 | B17: =Assumptions!B30*Assumptions!$B$5 -> 44000 | C17: =B17*Assumptions!$B$6 -> 132 | D17: =C17*Assumptions!$B$7 -> 19.8 | E17: =D17*(1-Assumptions!C30)*Assumptions!$B$8*Assumptions!D30 -> 0.297 | F17: =D17*Assumptions!C30*Assumptions!$B$11*Assumptions!D30 -> 0.1386 | G17: =E17*Assumptions!$B$9*Assumptions!$B$10+F17*Assumptions!$B$12*Assumptions!$B$13 -> 0.462825 | H17: =G17-Assumptions!$B$14 -> -22.537175 | I17: =SUM(E$6:E17) -> 1.838376 | J17: =Assumptions!B30*Assumptions!$C$5 -> 110000 | K17: =J17*Assumptions!$C$6 -> 660 | L17: =K17*Assumptions!$C$7 -> 165 | M17: =L17*(1-Assumptions!C30)*Assumptions!$C$8*Assumptions!D30 -> 4.125 | N17: =L17*Assumptions!C30*Assumptions!$C$11*Assumptions!D30 -> 1.65 | O17: =M17*Assumptions!$C$9*Assumptions!$C$10+N17*Assumptions!$C$12*Assumptions!$C$13 -> 10.68375 | P17: =O17-Assumptions!$C$14 -> -12.31625 | Q17: =SUM(M$6:M17) -> 25.533 | R17: =Assumptions!B30*Assumptions!$D$5 -> 275000 | S17: =R17*Assumptions!$D$6 -> 2750 | T17: =S17*Assumptions!$D$7 -> 962.5 | U17: =T17*(1-Assumptions!C30)*Assumptions!$D$8*Assumptions!D30 -> 38.5 | V17: =T17*Assumptions!C30*Assumptions!$D$11*Assumptions!D30 -> 14.4375 | W17: =U17*Assumptions!$D$9*Assumptions!$D$10+V17*Assumptions!$D$12*Assumptions!$D$13 -> 166.75313 | X17: =W17-Assumptions!$D$14 -> 143.75313 | Y17: =SUM(U$6:U17) -> 238.308
... A29: =Assumptions!A42 -> Sep 2028 | B29: =Assumptions!B42*Assumptions!$B$5 -> 92000 | C29: =B29*Assumptions!$B$6 -> 276 | D29: =C29*Assumptions!$B$7 -> 41.4 | E29: =D29*(1-Assumptions!C42)*Assumptions!$B$8*Assumptions!D42 -> 0.621 | F29: =D29*Assumptions!C42*Assumptions!$B$11*Assumptions!D42 -> 0.2898 | G29: =E29*Assumptions!$B$9*Assumptions!$B$10+F29*Assumptions!$B$12*Assumptions!$B$13 -> 0.967725 | H29: =G29-Assumptions!$B$14 -> -22.032275 | I29: =SUM(E$6:E29) -> 7.573176 | J29: =Assumptions!B42*Assumptions!$C$5 -> 230000 | K29: =J29*Assumptions!$C$6 -> 1380 | L29: =K29*Assumptions!$C$7 -> 345 | M29: =L29*(1-Assumptions!C42)*Assumptions!$C$8*Assumptions!D42 -> 8.625 | N29: =L29*Assumptions!C42*Assumptions!$C$11*Assumptions!D42 -> 3.45 | O29: =M29*Assumptions!$C$9*Assumptions!$C$10+N29*Assumptions!$C$12*Assumptions!$C$13 -> 22.33875 | P29: =O29-Assumptions!$C$14 -> -0.66125 | Q29: =SUM(M$6:M29) -> 105.183 | R29: =Assumptions!B42*Assumptions!$D$5 -> 575000 | S29: =R29*Assumptions!$D$6 -> 5750 | T29: =S29*Assumptions!$D$7 -> 2012.5 | U29: =T29*(1-Assumptions!C42)*Assumptions!$D$8*Assumptions!D42 -> 80.5 | V29: =T29*Assumptions!C42*Assumptions!$D$11*Assumptions!D42 -> 30.1875 | W29: =U29*Assumptions!$D$9*Assumptions!$D$10+V29*Assumptions!$D$12*Assumptions!$D$13 -> 348.66562 | X29: =W29-Assumptions!$D$14 -> 325.66562 | Y29: =SUM(U$6:U29) -> 981.708
A31: Year 1 (Oct 2026–Sep 2027) | B31: =SUM(B6:B17) -> 268000 | C31: =SUM(C6:C17) -> 804 | D31: =SUM(D6:D17) -> 120.6 | E31: =SUM(E6:E17) -> 1.838376 | F31: =SUM(F6:F17) -> 0.8395632 | G31: =SUM(G6:G17) -> 2.8281114 | H31: =SUM(H6:H17) -> -273.17189 | J31: =SUM(J6:J17) -> 670000 | K31: =SUM(K6:K17) -> 4020 | L31: =SUM(L6:L17) -> 1005 | M31: =SUM(M6:M17) -> 25.533 | N31: =SUM(N6:N17) -> 9.9948 | O31: =SUM(O6:O17) -> 65.28963 | P31: =SUM(P6:P17) -> -210.71037 | R31: =SUM(R6:R17) -> 1675000 | S31: =SUM(S6:S17) -> 16750 | T31: =SUM(T6:T17) -> 5862.5 | U31: =SUM(U6:U17) -> 238.308 | V31: =SUM(V6:V17) -> 87.4545 | W31: =SUM(W6:W17) -> 1019.2723 | X31: =SUM(X6:X17) -> 743.27228
A32: Year 2 (Oct 2027–Sep 2028) | B32: =SUM(B18:B29) -> 840000 | C32: =SUM(C18:C29) -> 2520 | D32: =SUM(D18:D29) -> 378 | E32: =SUM(E18:E29) -> 5.7348 | F32: =SUM(F18:F29) -> 2.67624 | G32: =SUM(G18:G29) -> 8.93673 | H32: =SUM(H18:H29) -> -267.06327 | J32: =SUM(J18:J29) -> 2100000 | K32: =SUM(K18:K29) -> 12600 | L32: =SUM(L18:L29) -> 3150 | M32: =SUM(M18:M29) -> 79.65 | N32: =SUM(N18:N29) -> 31.86 | O32: =SUM(O18:O29) -> 206.2935 | P32: =SUM(P18:P29) -> -69.7065 | R32: =SUM(R18:R29) -> 5250000 | S32: =SUM(S18:S29) -> 52500 | T32: =SUM(T18:T29) -> 18375 | U32: =SUM(U18:U29) -> 743.4 | V32: =SUM(V18:V29) -> 278.775 | W32: =SUM(W18:W29) -> 3219.8513 | X32: =SUM(X18:X29) -> 2943.8513
A33: 24 months total | B33: =SUM(B6:B29) -> 1108000 | C33: =SUM(C6:C29) -> 3324 | D33: =SUM(D6:D29) -> 498.6 | E33: =SUM(E6:E29) -> 7.573176 | F33: =SUM(F6:F29) -> 3.5158032 | G33: =SUM(G6:G29) -> 11.764841 | H33: =SUM(H6:H29) -> -540.23516 | J33: =SUM(J6:J29) -> 2770000 | K33: =SUM(K6:K29) -> 16620 | L33: =SUM(L6:L29) -> 4155 | M33: =SUM(M6:M29) -> 105.183 | N33: =SUM(N6:N29) -> 41.8548 | O33: =SUM(O6:O29) -> 271.58313 | P33: =SUM(P6:P29) -> -280.41687 | R33: =SUM(R6:R29) -> 6925000 | S33: =SUM(S6:S29) -> 69250 | T33: =SUM(T6:T29) -> 24237.5 | U33: =SUM(U6:U29) -> 981.708 | V33: =SUM(V6:V29) -> 366.2295 | W33: =SUM(W6:W29) -> 4239.1235 | X33: =SUM(X6:X29) -> 3687.1235
